{
  "schedule": [
    {
      "id": "dili",
      "name": "地理",
      "detail": "<h1>Hello this is 地理</h1>",
      "menu": [
        {
          "id": "1",
          "name": "第一部分: 自然地理",
          "detail": "<h2>Hello this is 自然地理</h2>",
          "menu": [
            {
              "id": "1-1",
              "name": "1-1"
            },
            {
              "id": "1-2",
              "name": "1-2"
            },
            {
              "id": "1-3",
              "name": "1-3"
            }
          ]
        }, {
          "id": "2",
          "name": "第二部分: 自地理",
          "detail": "<h2>Hello this is 自地理</h2>"
        }, {
          "id": "3",
          "name": "第三部分: 自理",
          "detail": "<h2>Hello this is 自理</h2>"
        }
      ]
    },
    {
      "id": "jishu",
      "name": "技术",
      "detail": "<h1>Hello this is 技术</h1>",
      "menu": [
        {
          "id": "1",
          "name": "第一部分: 技术",
          "detail": "<h2>Hello this is 技术</h2>"
        }, {
          "id": "2",
          "name": "第二部分: 技术",
          "detail": "<h2>Hello this is 技术</h2>"
        }, {
          "id": "3",
          "name": "第三部分: 技术",
          "detail": "<h2>Hello this is 技术</h2>"
        }
      ]
    },
    {
      "id": "yinyu",
      "name": "英语",
      "detail": "<h1>Hello this is 英语</h1>",
      "menu": [
        {
          "id": "1",
          "name": "第一部分: 英语",
          "detail": "<h2>Hello this is 英语</h2>",
          "menu": [{
            "id": "1-1",
            "name": "1-1",
            "detail": "1-1"
          }, {
            "id": "1-2",
            "name": "1-2",
            "detail": "1-2"
          }, {
            "id": "1-3",
            "name": "1-3",
            "detail": "1-3"
          }]
        }, {
          "id": "2",
          "name": "第二部分: 英语",
          "detail": "<h2>Hello this is 英语</h2>",
          "menu": [{
            "id": "1-1",
            "name": "1-1",
            "detail": "1-1"
          }, {
            "id": "1-2",
            "name": "1-2",
            "detail": "1-2"
          }, {
            "id": "1-3",
            "name": "1-3",
            "detail": "1-3"
          }]
        }, {
          "id": "3",
          "name": "第三部分: 英语",
          "detail": "<h2>Hello this is 英语</h2>",
          "menu": [{
            "id": "1-1",
            "name": "1-1",
            "detail": "1-1"
          }, {
            "id": "1-2",
            "name": "1-2",
            "detail": "1-2"
          }, {
            "id": "1-3",
            "name": "1-3",
            "detail": "1-3"
          }]
        }
      ]
    }
  ]
}